Metadata-Version: 1.2
Name: pandoc-extract-code
Version: 1.1.4
Summary: A pandoc filter to export each code block in a separate file
Home-page: https://gitlab.com/daamien/pandoc-extract-code
Author: Damien Clochard
Author-email: daamien@gmail.com
Maintainer: Damien Clochard
Maintainer-email: daamien@gmail.com
License: BSD
Download-URL: https://gitlab.com/daamien/pandoc-extract-code/archive/master.zip
Keywords: pandoc,filters,syntax,headers
Platform: UNKNOWN
Classifier: Development Status :: 5 - Production/Stable
Classifier: Operating System :: OS Independent
Classifier: Environment :: Console
Classifier: Intended Audience :: End Users/Desktop
Classifier: Intended Audience :: Developers
Classifier: Topic :: Software Development :: Build Tools
Classifier: Topic :: Software Development :: Documentation
Classifier: Topic :: Text Processing :: Filters
Classifier: Programming Language :: Python :: 2.7
Classifier: Programming Language :: Python :: 3.3
Classifier: Programming Language :: Python :: 3.4
Classifier: Programming Language :: Python :: 3.5
